<Properties StartupConfiguration="{1072CE00-0A2A-4475-9F84-A661256E53AB}|Default">
  <MonoDevelop.Ide.Workbench ActiveDocument="TaxCalculator/printReceipt.cs">
    <Files>
      <File FileName="TaxCalculator/printReceipt.cs" Line="10" Column="12" />
      <File FileName="TaxCalculator/Program.cs" />
      <File FileName="TaxCalculator/productInput.cs" />
      <File FileName="TaxCalculator/productDetails.cs" />
    </Files>
    <Pads>
      <Pad Id="ProjectPad">
        <State name="__root__">
          <Node name="TaxCalculator" expanded="True">
            <Node name="TaxCalculator" expanded="True">
              <Node name="printReceipt.cs" selected="True" />
            </Node>
          </Node>
        </State>
      </Pad>
    </Pads>
  </MonoDevelop.Ide.Workbench>
  <MonoDevelop.Ide.ItemProperties.TaxCalculator PreferredExecutionTarget="MonoDevelop.Default" />
  <MonoDevelop.Ide.DebuggingService.PinnedWatches />
  <MonoDevelop.Ide.Workspace ActiveConfiguration="Debug" />
  <MonoDevelop.Ide.DebuggingService.Breakpoints>
    <BreakpointStore />
  </MonoDevelop.Ide.DebuggingService.Breakpoints>
  <MultiItemStartupConfigurations />
</Properties>